[
    {
        "id": "ne555",
        "name": "NE555",
        "category": "Analog ICs",
        "description": "Precision timer/oscillator",
        "voltage": "4.5V-16V",
        "package": "DIP-8/SOP-8"
    },
    {
        "id": "lm358",
        "name": "LM358",
        "category": "Analog ICs",
        "description": "Dual operational amplifier",
        "voltage": "3V-32V",
        "package": "DIP-8/SOP-8"
    },
    {
        "id": "lm324",
        "name": "LM324",
        "category": "Analog ICs",
        "description": "Quad operational amplifier",
        "voltage": "3V-32V",
        "package": "DIP-14"
    }
]