[
    {
        "id": "led_red",
        "name": "Red LED",
        "category": "Optoelectronics",
        "description": "Basic red light indicator",
        "voltage": "1.8V-2.2V",
        "package": "5mm/0603"
    },
    {
        "id": "lcd1602",
        "name": "LCD1602",
        "category": "Optoelectronics",
        "description": "16x2 Character LCD",
        "voltage": "5V",
        "package": "Module"
    },
    {
        "id": "oled_i2c_096",
        "name": "OLED 0.96",
        "category": "Optoelectronics",
        "description": "I2C Blue/White OLED",
        "voltage": "3.3V-5V",
        "package": "Module"
    }
]